picohttp/__init__.py
picohttp/httpClasses.py
picohttp/httpClient.py
picohttp/httpServer.py
picohttp/staticResource.py
picohttp-0.0.11.dist-info/LICENSE
picohttp-0.0.11.dist-info/METADATA
picohttp-0.0.11.dist-info/WHEEL
picohttp-0.0.11.dist-info/top_level.txt
picohttp-0.0.11.dist-info/RECORD
